rpc_cli/__init__.py
rpc_cli/_cli.py
rpc_cli/py.typed
rpc_cli-2.2.3.dist-info/LICENSE
rpc_cli-2.2.3.dist-info/METADATA
rpc_cli-2.2.3.dist-info/WHEEL
rpc_cli-2.2.3.dist-info/RECORD
