Metadata-Version: 2.1
Name: rpc-cli
Version: 2.2.3
Summary: Expose methods of an RPC server through a CLI.
Home-page: https://gitlab.com/mburkard/rpc-cli
License: Apache-2.0
Author: Matthew Burkard
Author-email: matthewjburkard@gmail.com
Requires-Python: >=3.10,<4.0
Classifier: Intended Audience :: Developers
Classifier: License :: OSI Approved :: Apache Software License
Classifier: Programming Language :: Python :: 3
Classifier: Programming Language :: Python :: 3.10
Classifier: Programming Language :: Python :: 3.11
Classifier: Programming Language :: Python :: 3.12
Classifier: Topic :: Software Development
Classifier: Topic :: Software Development :: Libraries
Classifier: Topic :: Software Development :: Libraries :: Python Modules
Classifier: Typing :: Typed
Requires-Dist: cleo (>=2.0.1,<3.0.0)
Requires-Dist: openrpc (>=10.0.0,<11.0.0)
Requires-Dist: pydantic (>=2.4.0,<3.0.0)
Project-URL: Repository, https://gitlab.com/mburkard/rpc-cli
